[
  {
    "Id": 1,
    "Name": "bat",
    "Description": "A good bat",
    "Price": 120.00,
    "CategoryIds": [
      3
    ],
    "CategoryNames": [],
    "AvailableCategories": []
  },
  {
    "Id": 2,
    "Name": "ball",
    "Description": "A good ball",
    "Price": 20.00,
    "CategoryIds": [
      3
    ],
    "CategoryNames": [],
    "AvailableCategories": []
  },
  {
    "Id": 3,
    "Name": "speedometer",
    "Description": "A device to measure bowling speed",
    "Price": 300.00,
    "CategoryIds": [
      3,
      4
    ],
    "CategoryNames": [],
    "AvailableCategories": []
  },
  {
    "Id": 4,
    "Name": "smart phone",
    "Description": "good smart phone",
    "Price": 12.00,
    "CategoryIds": [
      4
    ],
    "CategoryNames": [],
    "AvailableCategories": []
  }
]